webcommander/__init__.py
webcommander/common/__init__.py
webcommander/common/sdk_conf.py
webcommander/common/sdk_console.py
webcommander/common/sdk_const.py
webcommander/common/sdk_util.py
webcommander/common/wc_exception.py
webcommander/http/__init__.py
webcommander/http/http_const.py
webcommander/http/http_requester.py
webcommander/http/wc_rest_processor.py
webcommander/sdlize/__init__.py
webcommander/sdlize/dto_base.py
webcommander/sdlize/wc_base_dto.py
webcommander/webcommander/__init__.py
webcommander/webcommander/webcommander_sdk.py
webcommander/webcommander/auth/__init__.py
webcommander/webcommander/auth/auth_api_url.py
webcommander/webcommander/auth/dto/__init__.py
webcommander/webcommander/auth/dto/token_dto.py
webcommander/webcommander/blog/__init__.py
webcommander/webcommander/blog/admin/__init__.py
webcommander/webcommander/blog/admin/admin_blog.py
webcommander/webcommander/blog/admin/admin_blog_api_url.py
webcommander/webcommander/categories/__init__.py
webcommander/webcommander/categories/admin/__init__.py
webcommander/webcommander/categories/admin/admin_categories.py
webcommander/webcommander/categories/admin/admin_categories_api_url.py
webcommander/webcommander/common/__init__.py
webcommander/webcommander/common/common_api_url.py
webcommander/webcommander/common/common_enum.py
webcommander/webcommander/common/dto/__init__.py
webcommander/webcommander/common/dto/address_dto.py
webcommander/webcommander/common/dto/blog_dto.py
webcommander/webcommander/common/dto/categories_dto.py
webcommander/webcommander/common/dto/common_dto.py
webcommander/webcommander/common/dto/country_dto.py
webcommander/webcommander/common/dto/currency_dto.py
webcommander/webcommander/common/dto/customers_dto.py
webcommander/webcommander/common/dto/discount_dto.py
webcommander/webcommander/common/dto/orders_dto.py
webcommander/webcommander/common/dto/product_dto.py
webcommander/webcommander/common/dto/settings_dto.py
webcommander/webcommander/common/dto/shipping_profiles_dto.py
webcommander-1.0.0.dist-info/LICENSE
webcommander-1.0.0.dist-info/METADATA
webcommander-1.0.0.dist-info/WHEEL
webcommander-1.0.0.dist-info/top_level.txt
webcommander-1.0.0.dist-info/RECORD
