Metadata-Version: 2.2
Name: webcommander
Version: 1.0.0
Summary: Webcommander SDK
Home-page: https://github.com/WebCommanderCMS/wc_python_sdk
Author: Ashiq Rahman
Author-email: ashiq@webalive.com.au
Project-URL: Documentation, https://developers.webcommander.com/
Platform: any
Classifier: Programming Language :: Python :: 3
Classifier: License :: OSI Approved :: MIT License
Classifier: Operating System :: OS Independent
License-File: LICENSE
Requires-Dist: requests==2.31.0
Requires-Dist: setuptools
Dynamic: author
Dynamic: author-email
Dynamic: classifier
Dynamic: description
Dynamic: description-content-type
Dynamic: home-page
Dynamic: platform
Dynamic: project-url
Dynamic: requires-dist
Dynamic: summary
